{
  "lastDownload": "2026-02-18T18:41:46.357Z",
  "duration": 1896,
  "status": {
    "debt": true,
    "demographics": true,
    "pensions": true,
    "budget": true
  },
  "sources": {
    "debt": {
      "success": true,
      "lastUpdated": "2026-02-18T18:41:45.032Z",
      "dataPoints": 373
    },
    "demographics": {
      "success": true,
      "lastUpdated": "2026-02-18T18:41:45.437Z"
    },
    "pensions": {
      "success": true,
      "lastUpdated": "2026-02-18T18:41:45.911Z",
      "dataPoints": 12
    },
    "budget": {
      "success": true,
      "lastUpdated": "2026-02-18T18:41:46.353Z",
      "years": 30
    }
  }
}